func_pckg/__init__.py
func_pckg/code_onetofive.py
func_pckg/code_sixtoten.py
csignal1to10gsrikanth-0.0.1.dist-info/LICENSE
csignal1to10gsrikanth-0.0.1.dist-info/METADATA
csignal1to10gsrikanth-0.0.1.dist-info/WHEEL
csignal1to10gsrikanth-0.0.1.dist-info/top_level.txt
csignal1to10gsrikanth-0.0.1.dist-info/RECORD
