Metadata-Version: 2.1
Name: csignal1to10gsrikanth
Version: 0.0.1
Summary: funcmethods
Home-page: UNKNOWN
Author: srikanth
Author-email: srikanth0466@gmail.com
License: UNKNOWN
Platform: UNKNOWN
Classifier: Programming Language :: Python :: 3
Classifier: License :: OSI Approved :: MIT License
Classifier: Operating System :: OS Independent
Requires-Python: >=3.7
